nix_visualize
