Metadata-Version: 1.1
Name: nix-visualize
Version: 1.0.4
Summary: CLI to automate generation of pretty Nix dependency trees
Home-page: https://github.com/craigmbooth/nix-dependency-visualizer
Author: Craig Booth
Author-email: craigmbooth@gmail.com
License: UNKNOWN
Download-URL: https://github.com/craigmbooth/nix-dependency-visualizer/tarball/1.0.4
Keywords: nix,matplotlib
Platform: UNKNOWN
